Metadata-Version: 1.1
Name: social-auth-core2
Version: 1.7.0
Summary: Python social authentication made simple. Add baidu Oauth
Home-page: https://github.com/dongkai1993/social-core
Author: Dong Kai
Author-email: dongkai1993@gmail.com
License: BSD
Keywords: openid,oauth,saml,social auth
Platform: UNKNOWN
Classifier: Development Status :: 4 - Beta
Classifier: Topic :: Internet
Classifier: License :: OSI Approved :: BSD License
Classifier: Intended Audience :: Developers
Classifier: Environment :: Web Environment
Classifier: Programming Language :: Python
Classifier: Programming Language :: Python :: 2.7
Classifier: Programming Language :: Python :: 3
